datatable/types.py
datatable/options.py
datatable/__init__.py
datatable/_build_info.py
datatable/time.py
datatable/str.py
datatable/re.py
datatable/internal.py
datatable/math.py
datatable/exceptions.py
datatable/xls.py
datatable/models.py
datatable/frame.py
datatable/utils/__init__.py
datatable/utils/fread.py
datatable/utils/misc.py
datatable/include/datatable.h
datatable/expr/__init__.py
datatable/expr/math.py
datatable/expr/reduce.py
datatable/expr/expr.py
datatable/lib/_datatable.cpython-310-x86_64-linux-gnu.so
datatable/lib/__init__.py
python-datatable-1.1.2.dist-info/RECORD
python-datatable-1.1.2.dist-info/METADATA
python-datatable-1.1.2.dist-info/LICENSE
python-datatable-1.1.2.dist-info/WHEEL
